zCtk/test/__init__.py
zCtk/test/test.py
zctk-0.0.0.5.dist-info/METADATA
zctk-0.0.0.5.dist-info/WHEEL
zctk-0.0.0.5.dist-info/top_level.txt
zctk-0.0.0.5.dist-info/RECORD
