Metadata-Version: 2.4
Name: zCtk
Version: 0.0.0.5
Author: zisia13
Author-email: nothing@nothing.com
Classifier: Programming Language :: Python :: 3
Classifier: License :: OSI Approved :: MIT License
Requires-Dist: customtkinter
Dynamic: author
Dynamic: author-email
Dynamic: classifier
Dynamic: requires-dist
